{
	"info": {
		"_postman_id": "dfbe10df-eed9-4730-818e-d058fa524846",
		"name": "spring-boot-modelmapper",
		"schema": "https://schema.getpostman.com/json/collection/v2.1.0/collection.json",
		"_exporter_id": "21205305"
	},
	"item": [
		{
			"name": "GET > All users",
			"request": {
				"method": "GET",
				"header": [],
				"url": {
					"raw": "http://localhost:8081/api/v1/users",
					"protocol": "http",
					"host": [
						"localhost"
					],
					"port": "8081",
					"path": [
						"api",
						"v1",
						"users"
					]
				}
			},
			"response": []
		},
		{
			"name": "GET > User by username",
			"request": {
				"method": "GET",
				"header": [],
				"url": {
					"raw": "http://localhost:8081/api/v1/users/john-doe",
					"protocol": "http",
					"host": [
						"localhost"
					],
					"port": "8081",
					"path": [
						"api",
						"v1",
						"users",
						"john-doe"
					]
				}
			},
			"response": []
		},
		{
			"name": "POST > New user",
			"request": {
				"method": "POST",
				"header": [],
				"body": {
					"mode": "raw",
					"raw": "{\r\n    \"username\": \"yourusername\",\r\n    \"email\": \"your@mail.com\"\r\n}",
					"options": {
						"raw": {
							"language": "json"
						}
					}
				},
				"url": {
					"raw": "http://localhost:8081/api/v1/users",
					"protocol": "http",
					"host": [
						"localhost"
					],
					"port": "8081",
					"path": [
						"api",
						"v1",
						"users"
					]
				}
			},
			"response": []
		}
	]
}